peptacular/__init__.py
peptacular/constants.py
peptacular/digestion.py
peptacular/element_setup.py
peptacular/errors.py
peptacular/fasta.py
peptacular/fragmentation.py
peptacular/glycan.py
peptacular/isotope.py
peptacular/mass_calc.py
peptacular/score.py
peptacular/spans.py
peptacular/types.py
peptacular/util.py
peptacular/chem/__init__.py
peptacular/chem/chem_calc.py
peptacular/chem/chem_constants.py
peptacular/chem/chem_util.py
peptacular/data/chem.txt
peptacular/data/gno.obo
peptacular/data/monosaccharides.obo
peptacular/data/monosaccharides_updated.obo
peptacular/data/psi-mod.obo
peptacular/data/resid.xml
peptacular/data/unimod.obo
peptacular/data/xlmod.obo
peptacular/mods/__init__.py
peptacular/mods/mod_db.py
peptacular/mods/mod_db_setup.py
peptacular/proforma/__init__.py
peptacular/proforma/input_convert.py
peptacular/proforma/proforma_dataclasses.py
peptacular/proforma/proforma_parser.py
peptacular/proforma/randomizer.py
peptacular/sequence/__init__.py
peptacular/sequence/combinatoric.py
peptacular/sequence/converters.py
peptacular/sequence/mod_builder.py
peptacular/sequence/sequence_funcs.py
peptacular-2.5.1.dist-info/licenses/LICENSE
peptacular-2.5.1.dist-info/METADATA
peptacular-2.5.1.dist-info/WHEEL
peptacular-2.5.1.dist-info/top_level.txt
peptacular-2.5.1.dist-info/RECORD
