Metadata-Version: 2.4
Name: peptacular
Version: 2.5.1
Summary: A spectacularly simple package for working with peptide sequences.
Author-email: Patrick Garrett <pgarrett@scripps.edu>
License: MIT License
Project-URL: repository, https://github.com/pgarrett-scripps/peptacular.git
Classifier: Programming Language :: Python :: 3
Classifier: Development Status :: 4 - Beta
Classifier: License :: OSI Approved :: MIT License
Classifier: Operating System :: OS Independent
Requires-Python: >=3.8
License-File: LICENSE
Requires-Dist: regex
Dynamic: license-file
